[{"items":[{"id":"m3","name":"Caesar Salad","price":"7.99","description":"Romaine lettuce tossed in Caesar dressing, topped with croutons and parmesan shavings.","image":"images/caesar-salad.jpg","quantity":1}],"customer":{"name":"Maxx Goldberg","email":"max@testmail.com","street":"Elm street","postal-code":"201501","city":"Noida"},"id":"743.1750502299706"},{"items":[{"id":"m3","name":"Caesar Salad","price":"7.99","description":"Romaine lettuce tossed in Caesar dressing, topped with croutons and parmesan shavings.","image":"images/caesar-salad.jpg","quantity":1}],"customer":{"name":"Maxx Goldberg","email":"max@testmail.com","street":"Elm street","postal-code":"201501","city":"Noida"},"id":"101.61588311324765"},{"items":[{"id":"m2","name":"Margherita Pizza","price":"12.99","description":"A classic pizza with fresh mozzarella, tomatoes, and basil on a thin and crispy crust.","image":"images/margherita-pizza.jpg","quantity":1},{"id":"m3","name":"Caesar Salad","price":"7.99","description":"Romaine lettuce tossed in Caesar dressing, topped with croutons and parmesan shavings.","image":"images/caesar-salad.jpg","quantity":1}],"customer":{"name":"Joe Goldberg","email":"joe@hotmail.in","street":"yuo","postal-code":"1123445","city":"la"},"id":"520.2818072623761"},{"items":[{"id":"m2","name":"Margherita Pizza","price":"12.99","description":"A classic pizza with fresh mozzarella, tomatoes, and basil on a thin and crispy crust.","image":"images/margherita-pizza.jpg","quantity":1},{"id":"m3","name":"Caesar Salad","price":"7.99","description":"Romaine lettuce tossed in Caesar dressing, topped with croutons and parmesan shavings.","image":"images/caesar-salad.jpg","quantity":1}],"customer":{"name":"Joe Goldberg","email":"joe@hotmail.in","street":"yuo","postal-code":"1123445","city":"la"},"id":"464.0964167138413"},{"items":[{"id":"m2","name":"Margherita Pizza","price":"12.99","description":"A classic pizza with fresh mozzarella, tomatoes, and basil on a thin and crispy crust.","image":"images/margherita-pizza.jpg","quantity":1},{"id":"m3","name":"Caesar Salad","price":"7.99","description":"Romaine lettuce tossed in Caesar dressing, topped with croutons and parmesan shavings.","image":"images/caesar-salad.jpg","quantity":1}],"customer":{"name":"Joe Goldberg","email":"joe@hotmail.in","street":"yuo","postal-code":"1123445","city":"la"},"id":"921.2312810916235"},{"items":[{"id":"m2","name":"Margherita Pizza","price":"12.99","description":"A classic pizza with fresh mozzarella, tomatoes, and basil on a thin and crispy crust.","image":"images/margherita-pizza.jpg","quantity":1},{"id":"m3","name":"Caesar Salad","price":"7.99","description":"Romaine lettuce tossed in Caesar dressing, topped with croutons and parmesan shavings.","image":"images/caesar-salad.jpg","quantity":1}],"customer":{"name":"Joe Goldberg","email":"joe@hotmail.in","street":"yuo","postal-code":"1123445","city":"la"},"id":"299.6090434784757"},{"items":[{"id":"m2","name":"Margherita Pizza","price":"12.99","description":"A classic pizza with fresh mozzarella, tomatoes, and basil on a thin and crispy crust.","image":"images/margherita-pizza.jpg","quantity":1},{"id":"m3","name":"Caesar Salad","price":"7.99","description":"Romaine lettuce tossed in Caesar dressing, topped with croutons and parmesan shavings.","image":"images/caesar-salad.jpg","quantity":1}],"customer":{"name":"Joe Goldberg","email":"joe@hotmail.in","street":"yuo","postal-code":"1123445","city":"la"},"id":"317.6449491720905"},{"items":[{"id":"m3","name":"Caesar Salad","price":"7.99","description":"Romaine lettuce tossed in Caesar dressing, topped with croutons and parmesan shavings.","image":"images/caesar-salad.jpg","quantity":1},{"id":"m2","name":"Margherita Pizza","price":"12.99","description":"A classic pizza with fresh mozzarella, tomatoes, and basil on a thin and crispy crust.","image":"images/margherita-pizza.jpg","quantity":1},{"id":"m1","name":"Mac & Cheese","price":"8.99","description":"Creamy cheddar cheese mixed with perfectly cooked macaroni, topped with crispy breadcrumbs. A classic comfort food.","image":"images/mac-and-cheese.jpg","quantity":1},{"id":"m4","name":"Spaghetti Carbonara","price":"10.99","description":"Al dente spaghetti with a creamy sauce made from egg yolk, pecorino cheese, pancetta, and pepper.","image":"images/spaghetti-carbonara.jpg","quantity":1},{"id":"m5","name":"Veggie Burger","price":"9.99","description":"A juicy veggie patty served on a whole grain bun with lettuce, tomato, and a tangy sauce.","image":"images/veggie-burger.jpg","quantity":1},{"id":"m6","name":"Grilled Chicken Sandwich","price":"10.99","description":"Tender grilled chicken breast with avocado, bacon, lettuce, and honey mustard on a toasted bun.","image":"images/grilled-chicken-sandwich.jpg","quantity":1}],"customer":{"name":"enns","email":"dgrg@drgertg","street":"Elm street","postal-code":"201501","city":"la"},"id":"311.8737126732898"},{"items":[{"id":"m3","name":"Caesar Salad","price":"7.99","description":"Romaine lettuce tossed in Caesar dressing, topped with croutons and parmesan shavings.","image":"images/caesar-salad.jpg","quantity":1},{"id":"m2","name":"Margherita Pizza","price":"12.99","description":"A classic pizza with fresh mozzarella, tomatoes, and basil on a thin and crispy crust.","image":"images/margherita-pizza.jpg","quantity":1},{"id":"m1","name":"Mac & Cheese","price":"8.99","description":"Creamy cheddar cheese mixed with perfectly cooked macaroni, topped with crispy breadcrumbs. A classic comfort food.","image":"images/mac-and-cheese.jpg","quantity":1},{"id":"m4","name":"Spaghetti Carbonara","price":"10.99","description":"Al dente spaghetti with a creamy sauce made from egg yolk, pecorino cheese, pancetta, and pepper.","image":"images/spaghetti-carbonara.jpg","quantity":1},{"id":"m5","name":"Veggie Burger","price":"9.99","description":"A juicy veggie patty served on a whole grain bun with lettuce, tomato, and a tangy sauce.","image":"images/veggie-burger.jpg","quantity":1},{"id":"m6","name":"Grilled Chicken Sandwich","price":"10.99","description":"Tender grilled chicken breast with avocado, bacon, lettuce, and honey mustard on a toasted bun.","image":"images/grilled-chicken-sandwich.jpg","quantity":1}],"customer":{"name":"enns","email":"fsdfsdfsfs@sdgsg","street":"Elm street","postal-code":"201501","city":"la"},"id":"700.4122351243129"},{"items":[{"id":"m1","name":"Mac & Cheese","price":"8.99","description":"Creamy cheddar cheese mixed with perfectly cooked macaroni, topped with crispy breadcrumbs. A classic comfort food.","image":"images/mac-and-cheese.jpg","quantity":1},{"id":"m3","name":"Caesar Salad","price":"7.99","description":"Romaine lettuce tossed in Caesar dressing, topped with croutons and parmesan shavings.","image":"images/caesar-salad.jpg","quantity":1},{"id":"m4","name":"Spaghetti Carbonara","price":"10.99","description":"Al dente spaghetti with a creamy sauce made from egg yolk, pecorino cheese, pancetta, and pepper.","image":"images/spaghetti-carbonara.jpg","quantity":1}],"customer":{"name":"Maxx Goldberg","email":"fsdfsdfsfs@sdgsg","street":"yuo","postal-code":"201501","city":"la"},"id":"57.40403484874768"}]